{
  "taskId": "57",
  "taskType": "issue",
  "target": "57-secrets-add-master-key-unlock-to-the-secrets-page",
  "outcome": "success",
  "exitCode": 0,
  "reason": "Re-verified prior implementation. All typecheck, lint, and unit/integration tests pass after merging main. No new code changes needed — feature already complete on this branch.",
  "prUrl": null,
  "runUrl": null,
  "filesTouched": [
    "src/dashboard/lib/vault/crypto.ts",
    "src/dashboard/lib/vault/store.ts",
    "src/dashboard/lib/components/SecretsManager.tsx",
    "app/api/kody/secrets/vault/route.ts",
    "tests/int/secrets-vault-route.int.spec.ts"
  ],
  "sessionLog": ".kody/last-run.jsonl",
  "startedAt": "2026-06-06T21:07:00.000Z",
  "finishedAt": "2026-06-06T21:10:00.000Z"
}
